README.txt
setup.py
src/z3c/__init__.py
src/z3c.pt.compat.egg-info/PKG-INFO
src/z3c.pt.compat.egg-info/SOURCES.txt
src/z3c.pt.compat.egg-info/dependency_links.txt
src/z3c.pt.compat.egg-info/namespace_packages.txt
src/z3c.pt.compat.egg-info/not-zip-safe
src/z3c.pt.compat.egg-info/requires.txt
src/z3c.pt.compat.egg-info/top_level.txt
src/z3c/pt/__init__.py
src/z3c/pt/configure.zcml
src/z3c/pt/compat/__init__.py
src/z3c/pt/compat/config.py
src/z3c/pt/compat/testing.py