Metadata-Version: 1.0
Name: z3c.pt.compat
Version: 0.3
Summary: Compatibility-layer for Zope Page Template engines.
Home-page: UNKNOWN
Author: Zope Corporation and Contributors
Author-email: zope3-dev@zope.org
License: ZPL
Keywords: zpt
Platform: UNKNOWN
Classifier: Framework :: Plone
Classifier: Framework :: Zope2
Classifier: Framework :: Zope3
Classifier: Programming Language :: Python
Classifier: Topic :: Software Development :: Libraries :: Python Modules
